{"84400":"Уж кто бы говорил 2","84401":"Уж кто бы говорил 2","84402":"Ужение окуня","84403":"Пьеса для пассажира","84404":"Раскаленное Рождество","84405":"Человек с бульвара Капуцинов","84406":"Фрирайдеры","84407":"Человек тьмы 3","84408":"Футбольные звезды","84409":"Человек-птица","84410":"Рыжая борода","84411":"Справедливый","84412":"Тина Тернер. Дикие сны (Tina Turner. Wildest Dreams). Концерт","84413":"Требования безопасности к действиям бригады АДС при механическом повреждении наружного газопровода","84414":"Титаник_","84415":"Третье чудо","84416":"Прогрессив Транс","84417":"Прямая и явная угроза /По роману Тома Клэнси/","84418":"Прямая и явная угроза /По роману Тома Клэнси/","84419":"Пятница 13-ое, часть 3","84420":"Приключения молодого Индианы Джонса. Война в пустыне","84421":"Приключения молодого Индианы Джонса. Война в пустыне","84422":"Психокоррекция личностных нарушений в дошкольном и школьном возрасте (ВФ.533)","84423":"Приключения Мышки","84424":"Приключения раввина Якова","84425":"Сан-Франциско (на английском языке)","84426":"Сердце предателя","84427":"Хедвиг и злосчастный дюйм","84428":"Хелло, Долли!","84429":"Хрустальный шар /По сказке братьев Гримм/","84430":"Цунами","84431":"Химия-8","84432":"Фитнесс-Дайджест 1. Базовая тренировка для женщины.","84433":"Хищники","84434":"Чайная церемония","84435":"Флиппер.","84436":"Третья сторона медали","84437":"Три брата","84438":"Тысяча чудес Вселенной","84439":"Телефон","84440":"Токио-Га","84441":"Лев зимой","84442":"Лев зимой","84443":"Лолита - 2000","84444":"Любовь и баскетбол","84445":"Легенда о Камелоте /По средневековым легендам/","84446":"Летчик от Бога (Николай Майданов)","84447":"Кубок","84448":"Свидетельница","84449":"Сериал \"И снова - 33 квадратных метра\"","84450":"Саттва весны","84451":"Сборник \"Айсберг\"","84452":"Страна святых чудес","84453":"Тайна женщины","84454":"Странная женщина","84455":"Суперзвезда","84456":"Суперзвезда","84457":"Царь Давид и Вирсавия","84458":"Хозяин № 4 (\"Записки детского онколога\") киноальманах","84459":"Царь царей","84460":"Час теней","84461":"Телепрограмма \"Последний герой\". 1-2 эпизод.","84462":"Частное расследование","84463":"Форт Апачи","84464":"Холодное лето пятьдесят третьего…","84465":"Цезарь и Клеопатра","84466":"Цель - идеальная фигура. Секреты красоты.","84467":"Луни Тьюнз снова в деле","84468":"Кукла.","84469":"Родня","84470":"Родственные души","84471":"Ребенок и уход за ним. Первые шаги","84472":"Ребенок и уход за ним. Первые шаги","84473":"Тайна рыцарей Дельты","84474":"Ставки сделаны","84475":"Странствия Одиссея","84476":"Суперновый Клип - 4","84477":"Суперпрофессионалы бокса. Международные бои. Часть 2.","84478":"Тайная крепость","84479":"Сталкер","84480":"Узы братства","84481":"Улыбка на лице (A Smiling Face) из серии \"Чердак сокровищ\"","84482":"Улыбка на лице (A Smiling Face) из серии \"Чердак сокровищ\"","84483":"Ущерб","84484":"Ущерб","84485":"Убежденный холостяк","84486":"Украсть красотку","84487":"Фаворит /По книге Лауры Хилленбранд \"Сухарь: легенда Америки\"/","84488":"Хороший, плохой, злой","84489":"Хороший, плохой, злой","84490":"Чудеса на виражах: Пираты и морское чудище","84491":"Эйс-Вентура. Розыск домашних животных. Держи хвост морковкой","84492":"Черный океан","84493":"Чужой билет","84494":"Дон Кихот возвращается","84495":"Рождественская история.","84496":"СМОТРИ (немецкий язык)","84497":"Рождественский ангел","84498":"Снова в школу","84499":"Слишком много (мало) любви"}