{"52200":"Кидалы.","52201":"Киевский вокзал","52202":"Кика","52203":"История \"неисторического\"","52204":"История 10 класс","52205":"История 11 класс","52206":"История Bad B. Часть 1. Начало русского хип-хопа.","52207":"История Bad B.Часть 2","52208":"История Бадди Холли","52209":"История Вернона и Ирен Кастл","52210":"История Гленна Миллера","52211":"История Гленна Миллера","52212":"История Гленна Миллера","52213":"История Гленна Миллера /По произведению Джорджа Саймона/","52214":"История Давида","52215":"История Джеймса Дина. Наконец-то… правда!","52216":"История Джо Луиса","52217":"История Джона Леннона","52218":"История Джона Леннона","52219":"История Золушки","52220":"История Золушки","52221":"История Золушки","52222":"История Иисуса Христа для детей","52223":"История Миркасыма Усманова","52224":"История Оливера/По роману Эрика Сигала/","52225":"История России  XX  век. Первая мировая война (14 - 22 серии)","52226":"История России ХХ век. Преддверие первой мировой войны.","52227":"История России ХХ век. Февральская революция","52228":"История России. ХХ век. Первая русская революция.","52229":"История России. ХХ век. Русско-Японская война.","52230":"История Российской Авиации. \"Соколы\" против \"Коршунов\"","52231":"История Уэнделла","52232":"История Элвиса Пресли: Юноша, мужчина, король","52233":"История автомобиля Феррари","52234":"История американского кино от Мартина Скорсезе","52235":"История английского кино от Стивена Фрирза","52236":"История бокса","52237":"История в Монте-Карло","52238":"История весеннего призыва","52239":"История воды","52240":"История государства Российского","52241":"История дворцов Русского музея. Виртуальные прогулки с Александром III (Летний домик Петра I, Строговский, Мраморный и  Михайловский дворцы, Михайловский замок, Летний дворец Петра  I)","52242":"История деревенского сторожа","52243":"История длиною в жизнь","52244":"История жизни","52245":"История игрушек 2","52246":"История игрушек 2","52247":"История из жизни кино. Россия","52248":"История картины \"Екатерина Нелидова\"","52249":"Зона 88","52250":"Зона безопасности","52251":"Зона удара","52252":"Зона.","52253":"Зоо-Олимпиада","52254":"Зоопарк (серии \"Подарок\", \"Подвиг\")","52255":"Зор Алеф \"Ответы непосвященному\"","52256":"Зорро.","52257":"Зорро. Новая эра","52258":"Зося","52259":"Зощенко и Олеша: двойной портрет в интерьере эпохи","52260":"Зоя","52261":"Зоя","52262":"Зоя.","52263":"Зубная фея","52264":"Зубы дракона.","52265":"Зуд седьмого года","52266":"Зулейха","52267":"Зур концерт","52268":"Зур концерт (Большой концерт)","52269":"Зэ Карл Верхейн Банд. Лив Ин Эль А (The Carl Verheyn Band - Live In L.A.)","52270":"И ангелы спускаются с небес","52271":"И в Париж (фильм-спектакль, содержит ненормативную лексику)","52272":"И в бедности и в богатстве","52273":"И в печали, и в радости.","52274":"И в печали, и в радости.","52275":"И вечно возвращаться…","52276":"И вечный вызов на ковер…","52277":"И вот пришел Бумбо","52278":"И вот пришел Бумбо…","52279":"И все-таки я верю","52280":"И все-таки я люблю …","52281":"И грянул гром /По рассказу Рэя Брэдберри/","52282":"И грянул гром /По рассказу Рэя Брэдберри/","52283":"И дождь омоет наши души","52284":"И дольше века длится жизнь","52285":"И есть, и будет","52286":"И как Икар","52287":"И корабль плывет","52288":"И мы как люди","52289":"И наступит завтра","52290":"И не осталось никого /По произведению Агаты Кристи \"Десять негритят\"/","52291":"И не осталось никого /По произведению Агаты Кристи \"Десять негритят\"/","52292":"И никто не узнает…","52293":"И осталось, как всегда, недосказанное что-то…","52294":"И падает снег…","52295":"И претерпевший до конца спасется","52296":"И пришел он /По одноименной новелле Френка Перетти/","52297":"Фабрика Чудес. Фильм пятый","52298":"Фабрика Чудес. Фильм третий","52299":"Фабрика Чудес. Фильм четвертый"}