{"20800":"Свет над Россией","20801":"Света \"Сердце моё\"","20802":"Светик","20803":"Светлана.","20804":"Скотланд, Пенсильвания","20805":"Скотч-терьер.","20806":"Скрипач","20807":"Скрипка","20808":"Скрипка Шехтеля","20809":"Скрытая любовь","20810":"Роковая судьба","20811":"Роковой выбор","20812":"Рокот неодобрения","20813":"Роксет \"Баллад энд поп хитс\"","20814":"Рокси Мьюзик. Высокая дорога (Roxy Music. High Road)","20815":"Рокси Мьюзик. Концерт в Аполло","20816":"Рокуэлл","20817":"Секрет Гудини. Анимационный сериал \"Смешарики-5\".","20818":"Секрет Щелкунчика","20819":"Секрет императора","20820":"Секрет лака Страдивари","20821":"Секретарь райкома","20822":"Секретная сила","20823":"Секретные дневники Гитлера","20824":"Секретные материалы Псов - шпионов (9-12 серии)","20825":"Секретные материалы Псов шпионов (1-4 серии)","20826":"Секретные материалы Псов шпионов (13-16 серии)","20827":"Секретные материалы Псов шпионов (17-20 серии)","20828":"Секретные материалы Псов шпионов (21-22 серии)","20829":"Секретные материалы Псов шпионов (5-8 серии)","20830":"Секретные материалы-Море душ","20831":"Секретные материалы-Продолжение","20832":"Русские сказки (сборник мультфильмов)","20833":"Русский & руссский","20834":"Русский бунт, бессмысленный и беспощадный","20835":"Русский взгляд на истории норвежской авиации","20836":"Русский заповедник","20837":"Русский и математика. Дошкольная подготовка","20838":"Русский и математика. Начальная школа","20839":"Русский модерн","20840":"Русский музей.","20841":"Русский охотник","20842":"Русский спецназ.","20843":"Русский фильм","20844":"Русский шансон","20845":"Русский шансон.","20846":"Русский язык. 6 - 8 классы","20847":"Семь","20848":"Салават \"Жырламый тузеп кара\" (Попробуй не петь)","20849":"Салма и Салим","20850":"Сало или 120 дней Содома","20851":"Салса с Джеффом и Леоной. Мамбо с Антоном Рыковым","20852":"Сальвадор /По произведению Франческо Эскрибано/","20853":"Сам","20854":"Самая большая семья","20855":"Самая красивая","20856":"Самая красивая - 2","20857":"Самая лучшая бабушка","20858":"Самая первая любовь","20859":"Самба Сюрпрайзес","20860":"Сильное влечение","20861":"Символика Краснодарского края","20862":"Симпли Ред. Звездная ночь с Симпли Ред","20863":"Симпли Рэд. Живой концерт в Лондоне","20864":"Симпли Рэд. Живой концерт в Сицилии","20865":"Симпли Рэд. Куба!","20866":"Симпли Рэд. Лучшие видео хиты","20867":"Скуби-Ду и Король Гоблинов","20868":"Скутер. Живой концерт в Берлине","20869":"Скутер. Полная коллекция видеоклипов","20870":"Слава Богу за всё. Крестный путь Святителя Иоанна Златоуста","20871":"Слава России - 2008","20872":"Сладкая парочка.","20873":"Стая акул","20874":"Стелс","20875":"Стенка на стенку","20876":"Степ аэробика \"Простые связки\"","20877":"Секретные материалы: Хочу верить","20878":"Секретные материалы: Хочу верить","20879":"Смертельный транс","20880":"Смерть Яна","20881":"Смерть в три дня","20882":"Смерть во сне (Смертельная опасность)","20883":"Смерть господина Лазареску","20884":"Смерть или жизнь","20885":"Семь братьев","20886":"Семь жизней","20887":"Семь колокольчиков","20888":"Семь смертей в кошачьем глазу","20889":"Семья .","20890":"Семья в осаде","20891":"Семья и Я. Приемная семья (фильм первый). Патронат (фильм второй).","20892":"Семья и дети из серии \"Каббала - шаг на встречу\"","20893":"Серая сова","20894":"Сербский Крест","20895":"Синбад-мореход.","20896":"Синдерелла. Рок и блюз. Лучшие видеохиты (Cinderella. Rocked, Wired & Bluesed: The Greatest Video Hits)","20897":"Синдикат смерти","20898":"Синеглазка.","20899":"Синие как море глаза"}