{"54400":"Улицы разбитых фонарей - 6. Августовский щипач.","54401":"Улицы разбитых фонарей - 6. Всё и сразу.","54402":"Улицы разбитых фонарей - 6. Гадалка.","54403":"Улицы разбитых фонарей - 6. Дуплет.","54404":"Улицы разбитых фонарей - 6. Его звали не Никита.","54405":"Улицы разбитых фонарей - 6. Игры для взрослых.","54406":"Улицы разбитых фонарей - 6. Конец квартала.","54407":"Улицы разбитых фонарей - 6. Лучший друг человека.","54408":"Улицы разбитых фонарей - 6. Мама","54409":"Улицы разбитых фонарей - 6. Мертвых не спросишь.","54410":"Улицы разбитых фонарей - 6. Несчастный случай.","54411":"Улицы разбитых фонарей - 6. Одиночный выстрел","54412":"Улицы разбитых фонарей - 6. Основная версия.","54413":"Улицы разбитых фонарей - 6. Падение рубля.","54414":"Улицы разбитых фонарей - 6. Пограничное состояние.","54415":"Улицы разбитых фонарей - 6. Портрет баронессы.","54416":"Улицы разбитых фонарей - 6. Последняя загадка.","54417":"Улицы разбитых фонарей - 6. Разбой на Фонтанке.","54418":"Улицы разбитых фонарей - 6. Роковой уик-энд.","54419":"Улицы разбитых фонарей - 6. Снайпер.","54420":"Улицы разбитых фонарей - 6. Убийство по рецепту.","54421":"Улицы разбитых фонарей - 6. Черный король.","54422":"Улицы разбитых фонарей-6. Вторая степень секретности.","54423":"Улицы разбитых фонарей-6. Общий наркоз.","54424":"Улицы разбитых фонарей-7. Большой приз.","54425":"Улицы разбитых фонарей-7. Вера, Надежда, Любовь.","54426":"Улицы разбитых фонарей-7. Високосный год.","54427":"Улицы разбитых фонарей-7. Женщина моей мечты.","54428":"Улицы разбитых фонарей-7. Инстинкт Леопольда.","54429":"Улицы разбитых фонарей-7. Источник информации.","54430":"Улицы разбитых фонарей-7. Ковер.","54431":"Улицы разбитых фонарей-7. Ловушка.","54432":"Улицы разбитых фонарей-7. Ментовский романс.","54433":"Улицы разбитых фонарей-7. Метод Фрейда.","54434":"Улицы разбитых фонарей-7. Мститель.","54435":"Улицы разбитых фонарей-7. По ту сторону рекламы.","54436":"Улицы разбитых фонарей-7. Подстава.","54437":"Улицы разбитых фонарей-7. Протекция.","54438":"Улицы разбитых фонарей-7. Профилактика.","54439":"Улицы разбитых фонарей-7. Пустяковое дело.","54440":"Улицы разбитых фонарей-7. Роковое похмелье.","54441":"Улицы разбитых фонарей-7. Скандал в благородном семействе.","54442":"Улицы разбитых фонарей-7. Случайное знакомство.","54443":"Улицы разбитых фонарей-7. Стрела судьбы.","54444":"Улицы разбитых фонарей-7. Третья жертва.","54445":"Улицы разбитых фонарей-7. Убийство, которого не было.","54446":"Улицы разбитых фонарей-7. Цена жизни.","54447":"Улицы разбитых фонарей-7. Человек за спиной.","54448":"Улицы разбитых фонарей-7. Чужие окна.","54449":"Улицы разбитых фонарей-7. Шестерка.","54450":"Улицы разбитых фонарей-8. Алиби.","54451":"Улицы разбитых фонарей-8. Татьянин день.","54452":"Улицы разбитых фонарей. Благие намерения","54453":"Улицы разбитых фонарей. Бои без правил","54454":"Улицы разбитых фонарей. Брачные узы","54455":"Улицы разбитых фонарей. Варя выходит замуж","54456":"Улицы разбитых фонарей. Высокие технологии","54457":"Улицы разбитых фонарей. Иголка в стоге сена","54458":"Тонкости подавляющей пластичной защиты","54459":"Тонулугэ уу кэллэ. Долгожданная вода Тюнгюлю.","54460":"Топ - топ. Гимнастика для детей 3 - 5 лет","54461":"Топ Гир: Дави на газ!","54462":"Топ Гир: Назад в левый ряд","54463":"Топаз","54464":"Топо - лесной человечек","54465":"Топор","54466":"Топчумба","54467":"Топчумба","54468":"Топчумба (сборник мультфильмов)","54469":"Топь","54470":"Тора! Тора! Тора!","54471":"Торгаши","54472":"Торговец","54473":"Торговец смертью.","54474":"Торговцы грезами (Никелоедон)","54475":"Торговцы славой","54476":"Тореадор в юбке","54477":"Торжество","54478":"Тори Эймос. Добро пожаловать в солнечную Флориду (Tori Amos. Welcome To Sunny Florida)","54479":"Тормоз","54480":"Тормоз","54481":"Тормозной путь","54482":"Торнадо","54483":"Торпедоносцы.","54484":"Тоска Вероники Фосс","54485":"Тоскующее сердце","54486":"Тот самый Бардин","54487":"Тот самый Ваня Солнцев. (Тайна базы \"Норд\")","54488":"Тот самый Хайт","54489":"Тот самый возраст","54490":"Тот самый день","54491":"Тот самый человек","54492":"Тотем","54493":"Тото в поисках дома","54494":"Тото. Полная коллекция клипов (Toto. The Ultimate Clip Collection)","54495":"Тотьма","54496":"Точка","54497":"Точка кипения","54498":"Точка опоры","54499":"Устрой себе похмелье"}