{"27460":"Энциклопедия собак: английский бульдог, колли, жестокошерстный фокстерьер, кавалер-кинг-чарльз-спаниель, английский спрингер спаниель","27461":"Энциклопедия собак: бладхаунд, йоркширский терьер, датский дог, ши-тцу, родезийский риджбек","27462":"Энциклопедия собак: боксер, бишон-фризе, ньюфаундленд, бигль, такса","27463":"Энциклопедия собак: ротвейлер, бостон-терьер, бассет-хаунд, шарпей, сенбернар","27464":"Энциклопедия собак: французский бульдог, пудель, эрдельтерьер, чихуахуа, лабрадор","27465":"ЕГОРИЙ ХРАБРЫЙ (проект \"Гора самоцветов\")","27466":"Мегамозг","27467":"Казачки не плачут. Людмила Хитяева.","27468":"Золотой капкан (1 - 16 серии)","27469":"МИР РУССКОЙ УСАДЬБЫ. Фильм 6-ой. Музыканты в усадьбе."}