{"55660":"Лучшие музыкальные клипы. Сборник 4 (Салман Кхан и Арджун Рампал).","55661":"Лучшие музыкальные клипы. Сборник 5 (Хиты 2006, часть 1)","55662":"Лучшие музыкальные клипы. Сборник 6. Саиф Али Кхан и Санджай Датт","55663":"Лучшие музыкальные клипы. Сборник 7 (Хиты 2006, часть 2)","55664":"Лучшие музыкальные клипы. Сборник 8 (Хиты 2007, часть 1)","55665":"Лучшие музыкальные клипы. Сборник 9 (Хиты 2007, часть 2)","55666":"Лучшие немецкие машины. BMW","55667":"Лучшие немецкие машины. Mercedes-Benz","55668":"Лучшие песни Русского Радио 2005. Видео","55669":"Лучшие песни Салман Кхана"}