{"27720":"Под руинами мавзолея","27721":"Продолжение души","27722":"Уроки безопасности на дорогах","27723":"Сборник. Удачный Шансон.","27724":"Звезды советского футбола. \"Валерий Маслов\". Звезды советского футбола. \"Виктор Царев\".","27725":"Звезды советского льда. \"Аркадий Чернышев\". Звезды советского льда. \"Виталий Давыдов\".","27726":"Возвращение в Брайдсхэд (по роману Ивлина Во)","27727":"Приключения Геркулеса в 3D (Приключения маленького Геркулеса в 3D)","27728":"Однажды в Версале","27729":"Соло для позвоночника"}