{"2800":"Эпицентр Ритмовремени","2801":"Одиссея сыщика Гурова","2802":"Анимационный фильм \"Смешарики 3Д\", серия \"Шуша\"","2803":"Анимационный фильм \"Смешарики 3D. Смешалости 2\", серия \"Хорошее настроение\"","2804":"Анимационный фильм \"Смешарики 3Д\", серия \"Последняя ошибка Пина\"","2805":"Костер на снегу","2806":"Взорвать СССР. Ядерный апокалипсис","2807":"Заочница","2808":"В ауте","2809":"Обучаю игре на гитаре","2810":"Майор","2811":"Верните музыку","2812":"В поисках утраченного праздника","2813":"Фитнес для лица с Аленой Россошинской. Омолаживающие техники для 30+","2814":"Китайская гимнастика со Станиславом Рогачёвым","2815":"Кундалини йога. Сила духа с Алексеем Меркуловым","2816":"Лорд. Пес - полицейский (серии 5-24)","2817":"Совсем не простая история","2818":"История СССР. Индустриализация","2819":"Safari Намибия. Фильм второй","2820":"А.Варум \"Сумасшедшая\"","2821":"Возвращение имён","2822":"Предчувствие_","2823":"Пацаны.","2824":"Твоя рука в моей руке","2825":"Пленница. Побег","2826":"Отвязные каникулы.","2827":"Улыбайся","2828":"Полный беспредел.","2829":"Paul McCartney. Rockshow","2830":"Умберто Джордано. Андре Шенье. Постановка фестиваля в Брегенце","2831":"Луи-Джозеф-Фердинанд Герольд. Тщетная предостороженность. Постановка Royal Opera House","2832":"День шакала","2833":"Каракал: Кошка-победитель","2834":"Волк повсюду","2835":"Пума: Американский лев","2836":"Росомаха: Последний призрак","2837":"Наталья Баннова \"От России до России\"","2838":"Лиза Вингард (сопрано, США), Борис Шнайдер (фортепиано, Швейцария)","2839":"1812: Уланская баллада","2840":"Нафкат Нигматуллин \"3 альбом 1 дискта\" (\"3 в 1\")","2841":"Паранормальное явление 4","2842":"На дороге /По роману Джека Керуака \"В дороге\"/","2843":"Петля времени","2844":"Мосгаз","2845":"Развод_","2846":"Детский юмористический киножурнал \"Ералаш\", выпуски 258 - 263","2847":"Адский бункер: Черное Солнце","2848":"После Люсии","2849":"Облачный атлас /По одноименному роману Дэвида Митчелла/","2850":"21 и больше (в переводе Гоблина)","2851":"Киллер Джо /По пьесе Трэйси Леттс/","2852":"Рождество с Чилли","2853":"Форсаж 6","2854":"Форсаж 6","2855":"Форсаж 6","2856":"Обливион","2857":"Поймай толстуху, если сможешь","2858":"Трансформеры: Прайм. Сезон 1. Части 1 - 2","2859":"Суррогат","2860":"Срочная доставка.","2861":"Шаян концерт \"Колик эле!\" (Веселый концерт \"Давай посмеемся\")","2862":"Яблочный спас","2863":"Мое любимое чудовище","2864":"Татарча солянка-30 (Татарская солянка-30).","2865":"Инспектор Беллами","2866":"Женщины-агенты","2867":"Элитный отряд","2868":"Полное затмение.","2869":"Гамбит_","2870":"Неуловимые","2871":"Последняя роль Риты","2872":"Солнцеворот","2873":"Новиков Александр. \"Девочка из лета\" (Концерт в \"Крокус Сити Холл\")","2874":"Репортаж из жизни растений","2875":"Отверженные /По одноименному произведению Виктора Гюго/","2876":"Отверженные /По одноименному произведению Виктора Гюго/","2877":"Отверженные /По одноименному произведению Виктора Гюго/","2878":"Кукольный дом_","2879":"Контуженый или уроки плавания вольным стилем","2880":"Контуженый или уроки плавания вольным стилем","2881":"Василиса Кожина","2882":"Уравнение любви","2883":"Выхожу тебя искать - 2","2884":"Владимир Высоцкий. \"Нет, ребята, всё не так...\" Избранные материалы документальной кинохроники. Части 1, 2, 3","2885":"Агент особого назначения - 4","2886":"Вспоминая 1942","2887":"Груффало /По мотивам книги Джулии Дональдсон и Алекса Шеффлера/","2888":"Берсерк: Золотой век. Фильм III: Сошествие","2889":"Пять сантиметров в секунду.","2890":"Александр Невский_.","2891":"Распутин.","2892":"Секс - за деньги, любовь - бесплатно","2893":"Тревожная кнопка","2894":"Тревожная кнопка","2895":"Грешники и Святые","2896":"Ограбление века.","2897":"Стрелы Купидона","2898":"Гость .","2899":"Гость ."}