{"50900":"Защита Чикирева","50901":"Защита от дурака","50902":"Защита против (серии 1 - 8)","50903":"Жених возвращается","50904":"Жених для Барби","50905":"Жених напрокат /По роману Элизабет Янг \"Сама напросилась\"/","50906":"Жених с прошлым","50907":"Женская азбука","50908":"Женская астрология или внеземное притяжение","50909":"Женская астрология или внеземное притяжение.","50910":"Женская извращенность","50911":"Женская интуиция","50912":"Женская интуиция","50913":"Женская интуиция - 2","50914":"Женская лига. Диск 1. Выпуски 1-4","50915":"Женская лига. Диск 1. Выпуски 5 - 8","50916":"Женская лига. Диск 1. Выпуски 9 - 12","50917":"Женская логика - 3","50918":"Женская логика - 4","50919":"Женская логика - 5","50920":"Женские монологи о войне","50921":"Женские тайны","50922":"Женское счастье или мужское достоинство","50923":"Женщина","50924":"Женщина - паук и Покахонтас","50925":"Женщина года","50926":"Женщина года","50927":"Женщина года","50928":"Женщина его мечты","50929":"Женщина есть женщина","50930":"Женщина ждет","50931":"Женщина завтрашнего дня","50932":"Женщина под дождем","50933":"Женщина с рыжими волосами","50934":"Женщина с ярмарки","50935":"Зеленая перчатка","50936":"Зеленинский погост","50937":"Зеленые береты","50938":"Зеленые цепочки","50939":"Зеленый дол.","50940":"Зеленый дракон","50941":"Зеленый лед","50942":"Зеленый фургон","50943":"Зеленый фургон","50944":"Зеленый фургон","50945":"Зелимхан","50946":"Землетрясение","50947":"Землетрясение.","50948":"Земля - воздух","50949":"Земля - воздух.","50950":"Коллекция (сериал) (1-8 серии)","50951":"Коллекция 2008 года пиротехнических изделий для профессионального использования","50952":"Коллекция 2008 года пиротехнических изделий развлекательного назначения","50953":"Коллекция № 1","50954":"Коллекция Оскар. 4 в 1 Вестерн. Выпуск 1 (Вива, Сапата! и др.)","50955":"Коллекция Оскар. 4 в 1 Вестерн. Выпуск 2 (Красная река и др.)","50956":"Коллекция Оскар. 4 в 1 Вестерн. Выпуск 3 (Барабаны долины Махонке и др.)","50957":"Коллекция Оскар. 4 в 1 Детектив/Триллер. Выпуск 1 (Газовый свет и др.)","50958":"Коллекция Оскар. 4 в 1 Детектив/Триллер. Выпуск 2 (Иностранный корреспондент и др.)","50959":"Коллекция Оскар. 4 в 1 Детектив/Триллер. Выпуск 3 (Тупик и др.)","50960":"Коллекция Оскар. 4 в 1 Детектив/Триллер. Выпуск 4 (Синий георгин и др.)","50961":"Коллекция Оскар. 4 в 1 Детектив/Триллер. Выпуск 5 (Призрак оперы и др.)","50962":"Коллекция Оскар. 4 в 1 Комедии. Выпуск 1 (Филадельфийская история и др.)","50963":"Коллекция Оскар. 4 в 1 Комедии. Выпуск 2 (С огоньком и др.)","50964":"Коллекция Оскар. 4 в 1 Комедии. Выпуск 3 (Огни рампы и др.)","50965":"Коллекция Оскар. 4 в 1 Комедии. Выпуск 4 (Энни получает ваше оружие и др.)","50966":"Коллекция Оскар. 4 в 1 Комедии. Выпуск 5 (Поднять якоря и др.)","50967":"Коллекция Оскар. 4 в 1 Мелодрамы. Выпуск 1 (Унесенные ветром и др.)","50968":"Коллекция Оскар. 4 в 1 Мелодрамы. Выпуск 2 (Марокко и др.)","50969":"Коллекция Оскар. 4 в 1 Мелодрамы. Выпуск 3 (Великий Зигфилд и др.)","50970":"Коллекция Оскар. 4 в 1 Мелодрамы. Выпуск 4 (Моя кузина Рейчел и др.)","50971":"Коллекция Оскар. 4 в 1 Мелодрамы. Выпуск 5 (Жених возвращается и др.)","50972":"Коллекция Оскар. 4 в 1 Фильмы о войне. Выпуск 1 (Отныне и во веки веков и др.)","50973":"Коллекция Оскар. 4 в 1 Фильмы о войне. Выпуск 2 (Вертикальный взлет и др.)","50974":"Коллекция Оскар. 4 в 1 Фильмы о войне. Выпуск 3 (Пески Иво Джимы и др.)","50975":"Коллекция Чарли Чаплина","50976":"Коллекция Чарли Чаплина. Том 2","50977":"Коллекция принцессы: Волшебный цветок","50978":"Коллекция принцессы: Магическое зеркало","50979":"Коллекция принцессы: Соперница Жасмин","50980":"Коллекция про Пиратов 4 в 1. Выпуск 1 (Красный корсар и др.)","50981":"Коллекция про Пиратов 4 в 1. Выпуск 2 (Один против всех и др.)","50982":"Коллекция про Пиратов 4 в 1. Выпуск 3 (Морской ястреб и др.)","50983":"Коллекция фантастики. Выпуск 1 (День, когда остановилась Земля и др.)","50984":"Колли","50985":"Колобков. Настоящий полковник!","50986":"Колобок","50987":"Колобок, колобок_","50988":"Колобок_","50989":"Коловращение жизни","50990":"Колокол, книга и свеча","50991":"Колокола Святой Марии","50992":"Колокольное искусство России","50993":"Колокольчик","50994":"Коломбо. Подходящий для рамки","50995":"Коломбо. Предписание: убийство","50996":"Коломбо. Этюд в черном","50997":"Жизнь с Луи (9 - 12 серии)","50998":"Жизнь с отцом.","50999":"Жизнь собак. Секреты собак. Язык собак. Наши лучшие друзья."}