{"30000":"Кунг-Фу Панда","30001":"На крючке","30002":"Солдаты неудачи","30003":"Трансформеры","30004":"Чарли и шоколадная фабрика /По книге Роальда Даля/","30005":"Шрэк третий","30006":"Александр Македонский_","30007":"Кислород (Фильм содержит сцены насилия)","30008":"Тайна Мунакра","30009":"Тайна Мунакра","30010":"Контрольные отпечатки","30011":"Обычаи и традиции осетин - алан (фильм 1 - Тайны Древнего Иристона","30012":"TOTAL. Live in TELE-CLUB (концерт группы \"TOTAL\")","30013":"Йогалатес. Основной курс","30014":"Йогалатес. Теряем вес","30015":"Йогалатес. Укрепляем мышцы","30016":"Событие (по пьесе В.Набокова)","30017":"Великие актёры в театре! Юрий Яковлев (Фауст и др.)","30018":"Великие актёры в театре! Валентин Гафт (Дом вдовца и др.)","30019":"4:0 в пользу Танечки","30020":"Что у Сеньки было.","30021":"Сын чемпиона","30022":"Золотые часы","30023":"Дубравка","30024":"Дайте нам мужчин","30025":"Включите северное сияние","30026":"Где ты, Багира?","30027":"Без сына не приходи!","30028":"Святая гора Афон","30029":"Псково-Печерский монастырь - дом Пресвятой Богородицы","30030":"Беседа с Архимандритом Тихоном (Секретаревым) наместником Псково-Печерского монастыря","30031":"Сборник \"Горячий лед\"","30032":"Дагестан. Древние ворота Кавказа","30033":"Основной инстинкт. Охота и рыбалка по всему миру","30034":"Безмолвный свидетель","30035":"Tomato Jaws - When I See U (Томатные челюсти - Когда я вижу тебя)","30036":"Олег Басилашвили. Мастер.","30037":"Долгое освобождение острова Борнхольм","30038":"ЭЭХХ, разгуляй! DVD 2009","30039":"Шестидесятник. Лев Кулиджанов","30040":"Легенды ночных стражей /По мотивам произведений Кэтрин Ласки \"Ночные стражи\"/","30041":"Хаббл 3D","30042":"30 дней ночи: Темные времена /Фильм содержит сцены насилия и жестокости/","30043":"Ешь, молись, люби /По книге Элизабет Гилберт/","30044":"Копы в глубоком запасе","30045":"Братство танца: Возвращение домой","30046":"Мальчики-налетчики","30047":"Обитель зла: Жизнь после смерти /Фильм содержит сцены насилия и жестокости/","30048":"Порча","30049":"Мачете","30050":"Времена года. Часть 1. Лето - Осень","30051":"Времена года. Часть 2. Зима - Весна","30052":"Евангелие от Матфея","30053":"Царь Эдип /По одноименной трагедии Софокла/","30054":"Солдатики","30055":"Марсианский дозор","30056":"Треугольник.","30057":"Генрих 4 Наваррский","30058":"Открытое море. Новые жертвы","30059":"ПРО ВАСИЛИЯ БЛАЖЕННОГО (проект \"Гора самоцветов\")","30060":"Паранормальные явления 2","30061":"Цыганская дорога","30062":"13.","30063":"Драма","30064":"Драма (фильм о фильме)","30065":"Если небо молчит","30066":"Джокер_","30067":"Маленькие Секреты Большого Бизнеса. Методика 1.1","30068":"Кочегар","30069":"Михайлов Стас \"На Бис!\"","30070":"Плюс Сибирь","30071":"Александр Радищев","30072":"Внутренний Татарстан","30073":"Возрождая звук","30074":"Немыслимое","30075":"Боги речного мира","30076":"Дракон: История Брюса Ли","30077":"Чаггингтон. Веселые паровозики. Станции активных действий","30078":"Сплит: Тайна крови. Выпуск 2","30079":"Сплит: Тайна крови. Выпуск 3","30080":"Эксперимент","30081":"Джек и Бобовый стебель","30082":"Глухарь. Возвращение (серии № 33 - 34)","30083":"Контекст, или искусство быть счастливым","30084":"Фиксики (серии 1 - 5)","30085":"Тростниковые жабы: Оккупация","30086":"Стоун","30087":"Зомби на диком Западе","30088":"Секрет соседа","30089":"За двумя зайцами.","30090":"Каштанка.","30091":"Весенняя сказка","30092":"Андрей и злой чародей","30093":"Удивительные приключения Дениса Кораблева","30094":"По секрету всему свету.","30095":"Второй. Герман Титов.","30096":"Загадки нашего Я","30097":"Сборник № 2","30098":"В поисках утраченного времени (Обретенное время)/По роману Марселя Пруста","30099":"Сон в летнюю ночь /По пьесе Шекспира/"}