{"95430":"ИИнтеллект. Начало","95431":"Кузбасс. Огненное сердце России","95432":"#ВишневыйСад: Первый Экологический Киноальманах","95433":"Петр I факты и мифы (серии: \"Зубы\", \"Новый год\", \"Подмена\", \"Рост\", \"Окно в Европу\", \"Картошка\", \"Рыжий\", \"Бородоруб\", \"Придурковатый вид\", \"Стройка\", \"Флот\", \"Бритье\", \"Алфавит\", \"Москва\", \"Коньки\", \"Тюльпаны\", \"14 ремесел\", \"Школа\", \"Ел руками\" и др.)","95434":"Сын","95435":"Без вины виноватая","95436":"Только по любви","95437":"Случайный брак","95438":"Бриллиантовое сердце","95439":"НОМЕР 69"}