{"74300":"Красота по-американски","74301":"Красота по-американски","74302":"Контроллинг ( ВЛ. 223 )","74303":"Контроль земли","74304":"Контроль разума","74305":"Контроль состояния изоляции подземных газопроводов аппаратурой АНПИ","74306":"Контрольный выстрел","74307":"Коси газон","74308":"Космическая Одиссея 2001 /По рассказу Артура К.Кларка/ (с субтитрами на русском языке) из \"Коллекции Стенли Кубрика\"","74309":"Космическая Одиссея 2001 года /По рассказу Артура К.Кларка/ (на английском языке)","74310":"Космическая катастрофа","74311":"Космическая катастрофа","74312":"Кончина","74313":"Конь белый","74314":"Кооператив \"Политбюро\", или будет долгим прощанье","74315":"Кооператив \"Политбюро\", или \"Будет долгим прощанье\"","74316":"Копейка","74317":"Копи царя Соломона","74318":"Копи царя Соломона","74319":"Копи царя Соломона /По произведению Х.Р.Хаггарда/","74320":"Котовский","74321":"Коттон Мэри","74322":"Коты Аристократы /По книге Тома МакКована и Тома Роува/","74323":"Коты Аристократы /По книге Тома МакКована и Тома Роува/ (на английском языке)","74324":"Коты не танцуют","74325":"Коты не танцуют","74326":"Ночной визит","74327":"Ночной дозор","74328":"Ночной дозор.","74329":"Ночной народ","74330":"Ночной народ","74331":"Ночной незнакомец","74332":"Ночной огонь","74333":"Крутой.","74334":"Крутой.","74335":"Крутые","74336":"Крутые братья","74337":"Крутые виражи","74338":"Крутые виражи","74339":"Крутые девчонки. Опасные пузыри","74340":"Крутые девчонки. Собачий денек","74341":"Крутые парни","74342":"Крутые перцы","74343":"Крутые стволы","74344":"Крутые стволы","74345":"Крушение","74346":"Крушение","74347":"Крушение 1","74348":"Крушение 1","74349":"Космическая морская пехота","74350":"Космическая одиссея 2001 года /По рассказу Артура К. Кларка/","74351":"Космическая одиссея 2001 года /По рассказу Артура К. Кларка/","74352":"Космическая одиссея 2001 года /По рассказу Артура К. Кларка/","74353":"Космические ковбои","74354":"Космические мстители","74355":"Крестный сын","74356":"Крестный сынок","74357":"Крестный: Лански","74358":"Крестовый поход. Каждую ночь мне снится дом","74359":"Крестовый поход. Наперегонки с ночью. Проблемы земли","74360":"Крестовый поход. Память войны. Они пришли с улицы","74361":"Кошачьи письма","74362":"Кошка - хозяйка дома","74363":"Кошка на раскаленной крыше","74364":"Кошка на раскаленной крыше","74365":"Кошка на раскаленной крыше /По одноименной пьесе Т.Уильямса/ (на английском языке)","74366":"Кошка на раскаленной крыше /по одноименной пьесе Т.Уильямса/","74367":"Кошки","74368":"Кошки - Мышки","74369":"Критический объект","74370":"Обратная сторона земли","74371":"Обратная сторона земли. Фильм 3. Поп и приход.","74372":"Обратно на Землю /По пьесе Гарри Сигелла/","74373":"Обратный билет","74374":"Обратный ход","74375":"Обрекающий на гибель","74376":"Обретай себя","74377":"Крушение 2","74378":"Крушение 2","74379":"Крушение 3","74380":"Крушение 3","74381":"Конго /По роману Майкла Крайтона/","74382":"Конго /По роману Майкла Крайтона/","74383":"Конгресс ФТСР \"Методика и практика развития танцевального спорта России\"","74384":"Конгресс ФТСР \"Теория и практика развития спортивного танца\"","74385":"Кондор","74386":"Конек - Горбунок","74387":"Конек - Горбунок","74388":"Конек - Горбунок.","74389":"Конек-Горбунок","74390":"Конец \"Сатурна\"","74391":"Конец Помпеи","74392":"Конец агента","74393":"Конец века. Хроники смутного времени.","74394":"Крестовый поход: Зона войны. Долгая дорога","74395":"Крестовый поход: Колодец вечности. Властвовать после смерти","74396":"Крестовый поход: Модель души. Внешность и другие обманы","74397":"Крестовый поход: Тропа скорби. Правила игры","74398":"Крестоносец","74399":"Крестоносцы"}