{"46390":"Сборник \"Кайнар 13\" (13 горячих хитов)","46391":"Сборник \"Кара кузлэрен\" (\"Черные глаза\")","46392":"Сборник \"Клиплар карыйбыз! (Смотри клипы!)","46393":"Сборник \"Кураж бэйрэм\" (Кураж-байрам)","46394":"Сборник \"Кучтэнэч\" (Гостиннец)","46395":"Сборник \"Лучшие песни русского радио 2004\"","46396":"Сборник \"Музыкаль бакча\" (Музыкальный сад)","46397":"Сборник \"Музыкаль бомба\" (Музыкальная бомба).","46398":"Сборник \"Музыкаль каймак\" (Самые лучшие песни)","46399":"Сборник \"Номер Один\" (Various Artists. Number One)"}