{"74100":"Корпорация \"Бессмертие\"","74101":"Корпорация монстров","74102":"Корпорация монстров","74103":"Корпорация монстров","74104":"Корпорация монстров","74105":"Коррупционер","74106":"Концерт квартета Игоря Бутмана из серии \"Живая коллекция\"","74107":"Концерт памяти М.Круга \"Исповедь\"","74108":"Кот в сапогах /По одноименной сказке Шарля Перро из сборника \"Сказки матушки Гусыни\"/","74109":"Кот в сапогах /По сказке братьев Гримм/","74110":"Кот в сапогах.","74111":"Кот в сапогах/По книге братьев Гримм/","74112":"Кот в сапогах/По книге братьев Гримм/","74113":"Кот, который умел петь","74114":"Кот-повар","74115":"Ночи с Клеопатрой","74116":"Ночная жизнь мистера Бампа","74117":"Ночная орхидея","74118":"Ночная посылка","74119":"Ночное вторжение","74120":"Ночное дежурство","74121":"Образы классики. Бах. Соборы молчания","74122":"Образы классики. Бах. Соборы молчания","74123":"Образы классики. Бетховен. Весенние цветы","74124":"Образы классики. Бетховен. Весенние цветы","74125":"Образы классики. Брукнер. Симфония природы","74126":"Образы классики. Брукнер. Симфония природы","74127":"Образы классики. Венецианский маскарад","74128":"Образы классики. Венецианский маскарад","74129":"Образы классики. Вивальди. Альпийская сказка","74130":"Образы классики. Вивальди. Альпийская сказка","74131":"Образы классики. Гендель. Волшебная Венеция","74132":"Образы классики. Гендель. Волшебная Венеция","74133":"Образы классики. Гендель. Дворцы королей","74134":"Образы классики. Гендель. Дворцы королей","74135":"Крупный калибр","74136":"Круто ты попал","74137":"Крутой","74138":"Крутой Джек","74139":"Крутой Джо","74140":"Крутой Джо","74141":"Крутой и смертоносный","74142":"Крутой маршрут","74143":"Крутой парень","74144":"Крутой парень","74145":"Крутой парень","74146":"Крутой стрелок","74147":"Компьютер в кроссовках","74148":"Корсиканские братья /По мотивам романа Александра Дюма/","74149":"Кортик","74150":"Кортик (по одноименной повести А. Рыбакова)","74151":"Коршуны добычей не делятся","74152":"Коршуны добычей не делятся","74153":"Крепость","74154":"Крепость /По роману Пола Уилсона/","74155":"Крепость 2","74156":"Крепость 2","74157":"Крепость 2","74158":"Крепость 2","74159":"Крепость 2","74160":"Крест римского центуриона","74161":"Крест римского центуриона","74162":"Крестная мать","74163":"Крестный 2: Вендетта","74164":"Крестный 4: Фальконе","74165":"Крестный отец /По одноименному роману Марио Пьюзо/","74166":"Крестный отец /По одноименному роману Марио Пьюзо/","74167":"Крестный отец /По одноименному роману Марио Пьюзо/","74168":"Крестный отец /По одноименному роману Марио Пьюзо/","74169":"Крестный отец 2 /По одноименному роману Марио Пьюзо/","74170":"Крестный отец 2 /По одноименному роману Марио Пьюзо/","74171":"Крестный отец 3 /По одноименному роману Марио Пьюзо/","74172":"Крестный отец 3 /По одноименному роману Марио Пьюзо/","74173":"Образы классики. Дворжак. Поэзия природы","74174":"Образы классики. Дворжак. Поэзия природы","74175":"Образы классики. Лист. Рапсодия свободы","74176":"Образы классики. Лист. Рапсодия свободы","74177":"Образы классики. Моцарт. Романтика Праги","74178":"Образы классики. Моцарт. Романтика Праги","74179":"Образы классики. Чайковский. Сияние гор","74180":"Образы классики. Чайковский. Сияние гор","74181":"Образы классики. Шопен. Нетронутый рай","74182":"Образы классики. Шопен. Нетронутый рай","74183":"Образы классики. Шопен. Осенний сон","74184":"Образы классики. Шопен. Осенний сон","74185":"Образы классики. Шопен. Сверкающий мир","74186":"Образы классики. Шопен. Сверкающий мир","74187":"Образы классики. Штраус. Чарующая Вена","74188":"Образы классики. Штраус. Чарующая Вена","74189":"Образы любви","74190":"Обратная сторона войны","74191":"Одя","74192":"Ожерелье для моей любимой","74193":"Компьютер для похорон","74194":"Комсомольск.","74195":"Кому я должен - всем прощаю","74196":"Конан - варвар","74197":"Конан - варвар","74198":"Конан и молодые воины","74199":"Конан-Разрушитель"}