{"62900":"Маленький купальщик","62901":"Маленький купальщик","62902":"Маленький лесной человек 2","62903":"Маленький магазинчик ужасов","62904":"Маленький патриот","62905":"Любовь на бегу.","62906":"Любовь на бегу.","62907":"Любовь на видео. Сборник клипов В.Преснякова.","62908":"Любовь не игрушка","62909":"Преображение","62910":"Преодоление","62911":"Преодоление предательства","62912":"Препоганая работа","62913":"Прерванная жизнь","62914":"Прерванная жизнь","62915":"Прерванная жизнь","62916":"Прерванная жизнь","62917":"Прерванная жизнь","62918":"Прерия /По роману Фенимора Купера/","62919":"Преследование","62920":"Преследование.","62921":"Праздник","62922":"Праздник Москва","62923":"Праздник Святого Иоргена","62924":"Отмороженные","62925":"Отмороженные","62926":"Отмороженные","62927":"Отмороженные.","62928":"Отмороженный профессор","62929":"Отмщение","62930":"Относительные ценности","62931":"Отныне и во веки веков /По одноименному роману Джеймса Джонса/ (на английском языке)","62932":"Оторви да брось","62933":"Отпетые мошенники","62934":"Отпетые мошенники","62935":"Отпуск в ноябре","62936":"Маленький солдат","62937":"Малибу","62938":"Манон 70 /По мотивам романа аббата Прево/","62939":"Мантэк Чиа. Космическое целительство.","62940":"Мантэк Чиа. Медитация мировой связи. Мудрый Цигун.","62941":"Мантэк Чиа. Мультиоргазмическая энергия.","62942":"Мантэк Чиа. Открытие третьего глаза. Специальные целительные практики.","62943":"Мантэк Чиа. Подготовительный Цигун. Космическое соединение по шести направлениям.","62944":"Мантэк Чиа. Рука Будды.","62945":"Любовь нельзя купить","62946":"Любовь нельзя купить","62947":"Любовь немолодого человека","62948":"Любовь плюс…","62949":"Любовь по Интернету","62950":"Любовь по заказу","62951":"Любовь по интернету.","62952":"Любовь по случаю","62953":"Любовь по случаю","62954":"Любовь по сценарию","62955":"Любовь под дождем","62956":"Любовь после полудня","62957":"Любовь после полудня","62958":"Любовь после полудня (на английском языке)","62959":"Любовь превыше всего","62960":"Любовь с первого взгляда","62961":"Праздник Сокровенного Имени","62962":"Праздник Штурвала Времени","62963":"Праздник на обочине","62964":"Праздник непослушания","62965":"Праздник новогодней елки (сборник мультфильмов)","62966":"Праздник.","62967":"Праздник_","62968":"Праздники сталинских соколов.","62969":"Отпуск за свой счет","62970":"Отпуск по ранению","62971":"Отпущение грехов","62972":"Отпущение грехов","62973":"Отражение","62974":"Отражение.","62975":"Отражения в золотом глазу","62976":"Отрицание любви ?","62977":"Отродье","62978":"Отроки во вселенной","62979":"Отроки во вселенной","62980":"Отроки во вселенной","62981":"Отроки во вселенной.","62982":"Мантэк Чиа. Создание поля Ци. Исцеление космическим цветом.","62983":"Мантэк Чиа. Целительная любовь.","62984":"Мантэк Чиа. Шесть целительных звуков. Очищение крови и лимфы.","62985":"Манускрипт ниндзя","62986":"Манфред Манн \"Станция Ангелов в Москве\"","62987":"Манчжурский кандидат /По произведению Ричарда Кондона/","62988":"Маньчжурский вариант","62989":"Маньяк","62990":"Маньяк - полицейский 3: знак молчания","62991":"Маньячные медсестры находят экстаз","62992":"Маппет-шоу из космоса","62993":"Маппет-шоу из космоса","62994":"Мара","62995":"Любовь с уведомлением","62996":"Любовь с уведомлением.","62997":"Любовь французская и русская","62998":"Любовь холоднее смерти","62999":"Любовь юной Нак"}