{"7100":"Рождественская история /По одноименному произведению Чарльза Диккенса/.","7101":"Алиса знает, что делать! (Приключение Алисы)","7102":"Вечеринка .","7103":"Мент в законе - 8","7104":"Евангелион 2.0: Ты (не) пройдешь (Евангелион 2.22: Ты (не) пройдешь)","7105":"Евангелион 3.0: Ты (не) исправишь (Евангелион 3.33: Ты (не) исправишь)","7106":"За облаками: Обещание юности","7107":"Афтершок","7108":"Титаны Ледникового периода","7109":"Пиратское телевидение","7110":"Линия Марты","7111":"Мечты сбываются однажды","7112":"ЕСТЬ У МУЗЫКИ НАЧАЛО","7113":"Спортивные истории (1 серия - История Белки, 2 серия - История Пуха)","7114":"Территория страха","7115":"Камчатка. Жизнь на вулкане","7116":"Конституционная практика","7117":"В гостях у афаров и исса. Вторая серия \"Афарская свадьба\"","7118":"Монако без яхт и казино","7119":"Земля, плененная верой. Серия 1","7120":"Земля, плененная верой. Серия 2","7121":"В гостях у афаров и исса.Первая серия \"Джибути - \"мал золотник, да дорог\"","7122":"Спартак _.","7123":"Людмила Зыкина. Бриллианты одиночества","7124":"Голубая кровь. Гибель империи","7125":"Проблема выбора","7126":"Леса России. Точка невозврата","7127":"Воля к жизни","7128":"Человек, создавший систему","7129":"Кузнецы Победы","7130":"Любите книгу","7131":"Взятки гладки_","7132":"Возвращение Мухтара - 2 (серии 519 - 614)","7133":"Лекарство против страха","7134":"Двое с пистолетами","7135":"Там, где есть счастье для меня","7136":"Старшая жена","7137":"Убийство Кеннеди. Новый след","7138":"Отель \"Президент\"","7139":"ВИС-ВИС ПУШАН ОРЛЫКЕМ (Печаль моя с запахом ромашки)","7140":"Управляя изменениями","7141":"Физика атомного ядра","7142":"MIRROS. LIGHT IN THE DARK. LIVE CONCERT.","7143":"Как поссорился Иван Иванович с Иваном Никифоровичем","7144":"Мечта.","7145":"Печали и радости мастера Иванова","7146":"Ведьмы из Сугаррамурди","7147":"Женщина может все","7148":"Шерлок Холмс (1 сезон)","7149":"Шерлок Холмс (2 сезон)","7150":"Остров смерти.","7151":"Болек и Лелек в Европе","7152":"Болек и Лелек - искатели приключений","7153":"Болек и Лелек - шахтеры","7154":"Капитан Клиппер","7155":"Кругосветное путешествие Болека и Лелека","7156":"Если любишь - прости","7157":"Тараканище","7158":"Непал форева","7159":"One Direction: Это мы.","7160":"Конец света 2013. Апокалипсис по-Голливудски.","7161":"Конец света 2013. Апокалипсис по-Голливудски.","7162":"Железный человек и Халк: Союз героев","7163":"Команда \"Мстители\": Мстители к бою","7164":"Самолеты.","7165":"Сказки на ночь_","7166":"Сокровище нации.","7167":"Хроники Нарнии: Принц Каспиан. /По произведению Клайва Стейплза Льюиса \"Хроники Нарнии\"/","7168":"Код Кирилла. Рождение цивилизации","7169":"2 + 2","7170":"Да здравствуют антиподы!","7171":"Железяки","7172":"Григорий Лепс - \"Полный вперед!\" (Юбилейный концерт в CROCUS CITY HALL  5 декабря 2012 года)","7173":"Вечный странник","7174":"Игра в правду","7175":"Цыпленок Цыпа.","7176":"Рататуй_","7177":"Приключения Флика.","7178":"Планета сокровищ.","7179":"Книга джунглей 2.","7180":"Все включено. Каникулы в Греции","7181":"Шальные деньги. Стокгольмский нуар","7182":"Философы: Урок выживания","7183":"Шесть раз","7184":"Однажды эта боль принесет тебе пользу","7185":"Тэйл","7186":"Угроза заражения","7187":"Приключения мастера кунг-фу","7188":"Плюс один.","7189":"Игра Эндера /По роману Орсона Скотта Карда/","7190":"Кастинг","7191":"Олдбой","7192":"Проклятое место 3D","7193":"ВИЙ 3D","7194":"Спортсмены золотой закалки","7195":"Машины сказки. Серия \"Конек-горбунок\"","7196":"Секреты манипуляции. Алкоголь","7197":"ВСЕ И СРАЗУ","7198":"Летняя ночь в Барселоне","7199":"Моздок. Перекрёсток истории"}