{"33190":"Сборник лучших фильмов Третьего Всероссийского фестиваля авторского короткометражного кино \"Арткино\". Диск-1","33191":"Сборник лучших фильмов Третьего Всероссийского фестиваля авторского короткометражного кино \"Арткино\". Диск-2","33192":"100 познавательных фильмов об электронике. Увлекательная электроника. Выпуск 1, диск 1.","33193":"Сборник лучших фильмов Третьего Всероссийского фестиваля авторского короткометражного кино \"Арткино\". Диск-3","33194":"Сборник лучших фильмов Третьего Всероссийского фестиваля авторского короткометражного кино \"Арткино\". Диск-4","33195":"100 познавательных фильмов об электронике. Увлекательная электроника. Выпуск 1, диск 2.","33196":"100 познавательных фильмов об электронике. Потребительская электроника. Выпуск 2, диск 1.","33197":"Мишень_","33198":"100 познавательных фильмов об электронике. Потребительская электроника. Выпуск 2, диск 2.","33199":"И не было лучше брата"}