{"47300":"Смерть отражается в кошачьем глазу","47301":"Смерть по завещанию","47302":"Смерть по прейскуранту","47303":"Смерть под парусом","47304":"Смерть супермоделям","47305":"Смерть шпионам","47306":"Смерш","47307":"Смех и наказание","47308":"Смех и наказание","47309":"Смехотерапия (концерт)","47310":"Смешарики - 2.  Водные процедуры","47311":"Смешарики - 2.  Что нужно всем","47312":"Смешарики - 2. Большие гонки","47313":"Смешарики - 2. Горы и конфеты","47314":"Смешарики - 2. Живые часы","47315":"Смешарики - 2. Играй, гармония !","47316":"Смешарики - 2. Как стать звездой","47317":"Смешарики - 2. Магнетизм","47318":"Смешарики - 2. Новые зубы Кроша","47319":"Смешарики - 2. Полеты во сне и наяву","47320":"Смешарики - 2. Последняя радуга","47321":"Смешарики - 2. Событие века","47322":"Смешарики - 2. Тайное общество","47323":"Смешарики - 2. Талисман","47324":"Смешарики - 2. Торжество разума","47325":"Смешарики - 2. Это сладкое слово \"Мёд\"","47326":"Смешарики - 3. Серия \"- 41 градус по Цельсию\"","47327":"Смешарики - 3. Серия \"Долгая рыбалка\"","47328":"Смешарики - 3. Серия \"Мисс Вселенная\"","47329":"Смешарики - 3. Серия \"Мыльная опера\"","47330":"Смешарики - 3. Серия \"ОРЗ\"","47331":"Прощайте, доктор Чехов !","47332":"Прощайте, фараоны!","47333":"Прощальная краса","47334":"Прощальное Эхо","47335":"Прощальное послание","47336":"Прощальное послание","47337":"Прощальные гастроли","47338":"Прощальный поцелуй","47339":"Прощание с Петербургом","47340":"Прудовая ловля по-английски","47341":"Прыг - скок. Гимнастика для детей 2-3 лет","47342":"Прыжки B.A.S.E. с горы Маттерхорн. Фильм VII кинофестиваля \"Вертикаль\"","47343":"Прыжки в воду (из цикла \"Олимпиада-80\")","47344":"Прыжки с трамплина (из цикла \"Спорт\")","47345":"Прыжок","47346":"Прыжок с крыши","47347":"Прыжок.","47348":"Прямое попадание","47349":"Пряник","47350":"Псевдоним \"Албанец\"","47351":"Псих","47352":"Психик ТВ. Время живет (Psychic TV. Time's UP Live)","47353":"Психоз.","47354":"Совсем как папочка!","47355":"Совсем не ангел","47356":"Соглашение","47357":"Содом и Гоморра_","47358":"Содом. Лордс оф Деправити (Sodom. Lords of Depravity)","47359":"Содрогание","47360":"Создавая возможности. Видеокурс английского языка (Creating Opprtunities)","47361":"Создание и укрепление сосудов тела. 64 сосуда. Второй шаг к здоровью. № 72. 20 марта 2005 г.","47362":"Создания ночи","47363":"Созданы друг для друга","47364":"Созданы друг для друга","47365":"Созданы друг для друга.","47366":"Создатели и Зрители. Выпуск 1","47367":"Создатели и Зрители. Выпуск 2","47368":"Создатели и Зрители. Выпуск 3","47369":"Создатели и Зрители. Выпуск 4","47370":"Создатели тени","47371":"Сокровища Алмазного Фонда","47372":"Сокровища Аляски","47373":"Сокровища Да Винчи","47374":"Сокровища Древней Греции","47375":"Сокровища России","47376":"Сокровища Сьерра Мадре","47377":"Сокровища Сьерра Мадре","47378":"Сокровища Сьерра Мадре","47379":"Сокровища древнего храма","47380":"Сокровища древнего храма","47381":"Сокровища императора. Волшебник страны Оз","47382":"Сокровища святого Януария","47383":"Сокровище","47384":"Сокровище Амазонки","47385":"Сокровище Амазонки","47386":"Сокровище Амазонки","47387":"Сокровище нации","47388":"Сокровище нации","47389":"Сокровище нации","47390":"Сокровище нации","47391":"Сокровище нации","47392":"Сокровище нации: Книга тайн","47393":"Сокровище погибшего коробля","47394":"Сокровище серебряного озера","47395":"Сокрушивший римлян","47396":"Сокрушитель","47397":"Сокуров","47398":"Солдат","47399":"Солдат Бога"}