{"93800":"Веном 2","93801":"Титан","93802":"Курорт","93803":"Монстр: Начало","93804":"Я никого не ем","93805":"Момент истины","93806":"Лесные истории","93807":"Гибель империи. Российский урок","93808":"Опасный попутчик","93809":"Похищенный","93810":"Полу-Нельсон","93811":"Спроси у пыли","93812":"Клуб \"Завтрак\"","93813":"Ромео и Джульетта","93814":"Видеопризраки","93815":"Игрушки Амитивилля","93816":"Открытая рана","93817":"Чужие против Титаника","93818":"Сэнит Зон","93819":"Я погиб под Демянском","93820":"Анимационный сериал \"Лунтик\" серии 515-526","93821":"Кощей. Начало","93822":"Анимационный сериал \"Лунтик\" серия 527 ","93823":"Турбозавры (сезон 1, 2)","93824":"Идеальная жена","93825":"МУЛЬТ в кино. Выпуск № 131","93826":"Телохранитель","93827":"Ключ от всех дверей (1 – 16 серии)","93828":"Теорема Зеро","93829":"Семейный бюджет","93830":"Больше, чем любовь. Одиночество Линдгрен","93831":"Истории Долли","93832":"Дело Мадсена","93833":"Экипаж 314","93834":"Приключения на шоколадной фабрике","93835":"Проклятье Эбигейл","93836":"Эйфель","93837":"Афины","93838":"Криптополис","93839":"Пушистые спасатели","93840":"Проклятый Хэллоуин","93841":"Прыгучая братва","93842":"Робот Ари","93843":"Прокуроры 7 \"БЕЗ СРОКА ДАВНОСТИ. ЖЕРТВОПРИНОШЕНИЕ. ДЕТИ\"","93844":"Прокуроры 7 \"БЕЗ СРОКА ДАВНОСТИ. БРЯНСКИЙ БУХЕНВАЛЬД\"","93845":"Прокуроры 7 \"БЕЗ СРОКА ДАВНОСТИ. АДСКИЙ КОЛОДЕЦ\"","93846":"Прокуроры 7 \"БЕЗ СРОКА ДАВНОСТИ. УЦЕЛЕВШИЕ\"","93847":"Пауза в Санкт-Петербурге","93848":"Агафья","93849":"Нас всех убьёт глобальное потепление","93850":"Вырастешь - поймёшь","93851":"Мимо воды","93852":"Ван Гог и Япония","93853":"Программа короткометражных фильмов OSCAR 2021","93854":"Репортер на краю света","93855":"Как выйти замуж за сантехника","93856":"Хищники. Большие и редкие","93857":"Вторжение живой стали","93858":"Детектив на миллион. Расплата","93859":"Охотник","93860":"Я плюю на ваши могилы 2","93861":"Снежный барс. Белый отшельник","93862":"Батя","93863":"Купер. Непойманный","93864":"Момент","93865":"Инсайт","93866":"Александр Матросов. Шагнувший в бессмертие","93867":"Самцы","93868":"Ястреб-тетеревятник. Душа ветра","93869":"Отряд А. Игрушки-спасатели","93870":"Толстяк","93871":"Просто представь, что мы знаем","93872":"Страна гор","93873":"ЗАВТРА БЫЛ КОВИД","93874":"Петербург 91/21","93875":"на тебе сошелся клином белый свет","93876":"Ветеринарка","93877":"Вопреки очевидному","93878":"Долли и друзья (оригинальные серии)","93879":"Космический рейс. Миссия на Марс","93880":"Эксклюзив","93881":"Исход","93882":"Враг государства № 1","93883":"Мир занимательных игр с ребёнком. Изучаем русский алфавит","93884":"Враг государства № 1: Легенда","93885":"Добыча","93886":"В компании мужчин","93887":"Гуманитарные науки","93888":"Каньоны","93889":"Мрачные небеса","93890":"Решения","93891":"Не время умирать","93892":"Семейка Аддамс: Горящий тур","93893":"Суперзвезда","93894":"Богема 2021","93895":"Музыкальная коллекция","93896":"Юбилей. Михаилу Ковальчуку 75","93897":"ИДОЛЫ ЕНИСЕЯ","93898":"Элли","93899":"Небо"}