{"67460":"Великие цивилизации: Китай. История и культура городов Пекин, Чжанчжоу, Хухехоате","67461":"Великие цивилизации: Китай. История и культура городов Пиньяо, Гаунчжоу, Цюаньчжоу, Шанхай, Чунцин","67462":"Великие цивилизации: Китай. История и культура городов Пиньяо, Гаунчжоу, Цюаньчжоу, Шанхай, Чунцин","67463":"ВЛАСТЬ","67464":"ВМХ: Хороший, плохой, злой","67465":"Величайшие вершины мира","67466":"Величайшие катастрофы Америки","67467":"Величайшие катастрофы Америки","67468":"Бриллианты навечно /По книге Яна Флеминга/","67469":"Бриллианты навечно /По книге Яна Флеминга/"}