{"70400":"Два придурка в Голливуде","70401":"Джек-потрошитель возвращается","70402":"Джеки Браун /По мотивам книги Элмора Леонарда \"Пунш из рома\"/","70403":"Джеки Чан: Моя жизнь","70404":"Джем","70405":"Дженесис. Песенник (Genesis. Songbook)","70406":"Дженнифер 8 следующая","70407":"Дженнифер 8 следующая","70408":"Дженнифер Лопес. Давайте погромче (Jennifer Lopez. Let's get loud)","70409":"Джентльмены предпочитают блондинок","70410":"Джентльмены предпочитают блондинок","70411":"Джентльмены удачи","70412":"Джеремия Джонсон /По роману Вардиса Фишера \"Человек гор\"/","70413":"Женщина-обезьяна","70414":"Женщина-призрак /По роману Уильяма Айриша/","70415":"Женщина-призрак /По роману Уильяма Айриша/","70416":"Женщины","70417":"Женщины в черном","70418":"Девственницы-самоубийцы","70419":"Девушка N 6","70420":"Девушка без адреса","70421":"Детектив Шафт /По одноименному роману Эрнста Тайдимена/","70422":"Детектив Шафт /По одноименному роману Эрнста Тайдимена/","70423":"Детектив Шафт /По одноименному роману Эрнста Тайдимена/","70424":"Детектив Шимпански","70425":"Детектив по-русски","70426":"Детективный дуэт","70427":"Детективы","70428":"Детектор лжи","70429":"Детектор лжи","70430":"Два рояля. Коллекция : Л.Долина, В.Сюткин, О.Газманов, Л.Дэнс.","70431":"Два рояля. Коллекция : Л.Черникова, И.Саруханов, Валерия, Н.Трубач.","70432":"Два рояля. Коллекция : Шоу группа \"Доктор Ватсон\".","70433":"Два сердца, одна корона","70434":"Два солдатика бумажных","70435":"Два способа наколки","70436":"Два товарища","70437":"Два убийцы","70438":"Двадцатый век начинается","70439":"Двадцать баксов","70440":"Двадцать восемь дней","70441":"Двадцать восемь дней","70442":"Двадцать восемь дней","70443":"Двадцать восемь дней","70444":"Двадцать восемь дней","70445":"Девять с половиной недель","70446":"Девять с половиной недель","70447":"Девять с половиной недель","70448":"Джерри","70449":"Для чего мы становимся родителями","70450":"Для чего мы учим мир","70451":"Для чего нужны семена?","70452":"Дмитрий Донской","70453":"Дмитрий Кантемир","70454":"Дневная красавица","70455":"Дневник Бриджет Джонс /По мотивам романа Хелен Филдинг/","70456":"Дневник Бриджет Джонс /По мотивам романа Хелен Филдинг/","70457":"Дневник баскетболиста или Баскетбольные записки /По роману Джима Кэррола/","70458":"Дневник его жены","70459":"Дневник его жены","70460":"Дневник его жены.","70461":"Женщины на грани нервного срыва","70462":"Женщины ночи","70463":"Допустимый риск /По роману Робина Кука/","70464":"Дора-Дора-помидора","70465":"Дореми","70466":"Дорз","70467":"Дорз","70468":"Дориан Грей /По рассказу Оскара Уайлда \"Портрет Дориана Грея\"/","70469":"Дорога","70470":"Дорога","70471":"Дорога ангелов","70472":"Дорога в Занзибар","70473":"Дорога в Марокко","70474":"Дорога в Парадиз","70475":"Дорога в Рио","70476":"Дорога в Сингапур","70477":"Дорога в ад","70478":"Дети Белой могилы","70479":"Дети Биби /По одноименной книге Робина Хэрриса/","70480":"Дети Биби /По одноименной книге Робина Хэрриса/","70481":"Дети Дон-Кихота","70482":"Дети Дюны (По романам Фрэнка Герберта)","70483":"Дети Революции","70484":"Дикарь","70485":"Дикарь.","70486":"Дикарь_","70487":"Дикая Америка","70488":"Дикая Америка","70489":"Девять ярдов","70490":"Дед Мороз - отморозок","70491":"Дед Мороз и лето","70492":"Дедушка и внучек /новая версия/","70493":"Дедушка хороший, но…не говорит, куда спрятал деньги","70494":"Дежа вю","70495":"Дежа вю.","70496":"Дневник его жены_","70497":"Дневник камикадзе","70498":"Двенадцать месяцев","70499":"Двенадцать месяцев"}