{"18300":"Душой исполненный полет","18301":"В мире танца.","18302":"России светлая душа","18303":"Улыбка Терпсихоры","18304":"Царь","18305":"Наши дети","18306":"Семнадцать мгновений весны. Цветная версия.","18307":"Танго с ангелом","18308":"Карамазовы (фильм-спектакль Московского академического театра им.Вл.Маяковского)","18309":"Где обедал воробей","18310":"Гора.","18311":"Таёжный роман","18312":"Московский Чрезвычайный Сокрушительный","18313":"Теория хаоса","18314":"Уроки рыболова (61-63 серии)","18315":"Джошуа.","18316":"Бей и беги","18317":"Большой переполох в Маленьком Китае","18318":"День, когда Земля остановилась.","18319":"27 свадеб","18320":"Пока ее не было","18321":"Человек, который любит","18322":"Удивительная легкость","18323":"100 футов","18324":"Забытые желания","18325":"Возвращение блудного сына","18326":"Сплетенные параллели","18327":"Твист снова в Москве","18328":"Россия","18329":"Цивилизация","18330":"Топ Гир: Наперегонки к Северному полюсу","18331":"Любовный напиток № 9","18332":"Джон Кеннеди: Рандеву со смертью","18333":"Кэти Смит: Гибкая, стройная, сильная","18334":"Тетка","18335":"Куба. Главы неопубликованной книги ... Фильм 1, 2.","18336":"Animalджаz. Live in TELE-CLUB","18337":"Любимые Застольные Праздники - 2","18338":"МАМОНОВ и АЛЕКСЕЙ","18339":"Про Красную Шапочку","18340":"Вампиры: Возрождение древнего рода","18341":"Вампиры: жажда крови","18342":"Вампиры: жажда крови","18343":"Ван Гог не виноват","18344":"Ван Хален. Видео хиты. Часть 1","18345":"Ван Хален. Живьем без сети","18346":"Ван Хален. Здесь и сейчас","18347":"Ваниль и шоколад","18348":"Ванька","18349":"Ванька Грозный","18350":"Ванюша и Великан","18351":"Ванюша и космический пират","18352":"Варварины свадьбы","18353":"Варвары. Викинги","18354":"Варвары. Готы","18355":"Варвары. Монголы","18356":"Варвары.Гуны","18357":"Варежки","18358":"Варенька","18359":"Васаби.","18360":"Васильевский остров","18361":"Ватель","18362":"Ваш В.Пудовкин","18363":"Ваша Бриташа. Сезон 1(эпизод 1-8)","18364":"Ваша остановка мадам","18365":"Новая Земля","18366":"Новая жизнь сыщика Гурова","18367":"Новая колония","18368":"Новая семейка Аддамс (1-4 серии)","18369":"Новая семейка Аддамс (13-16 серии)","18370":"Новая семейка Аддамс (17-20 серии)","18371":"Новая семейка Аддамс (21-24 серии)","18372":"Новая семейка Аддамс (25-26 серии)","18373":"Новая семейка Аддамс (5-8 серии)","18374":"Новая семейка Аддамс (9-12 серии)","18375":"Новая эра","18376":"Новгородцы","18377":"Новейшая история \"Место встречи. 20 лет спустя\"","18378":"Новичок .","18379":"Ново-Валаамский монастырь в Финляндии","18380":"Новогоднее похищение (Похищение (2 части). Это было, было…улыбки 60-х. Предновогоднее выступление Л.И.Брежнева по ЦТ.)","18381":"Новогодняя засада","18382":"Новогодняя ночь","18383":"Новые времен, или биржа недвижимости","18384":"Новые мстители: Герои завтрашнего дня","18385":"Новые муравьи в штанах","18386":"Билл Виман и короли ритма. Хорошее время для ролла","18387":"Билли Айдол. Выступление на  VH1","18388":"Биржевая игра. Уроки мастерства от Александра Элдера.","18389":"Бисероплетение для девчонок и мальчишек. Подвески, брелоки, украшения своими руками.","18390":"Битва за Библию","18391":"Битва за огонь","18392":"Ангелы смерти. Часть 2","18393":"Близкие друзья","18394":"Немного любви, немного магии","18395":"Падший ангел (путь женщины)","18396":"Отчаянные","18397":"Встреча, подарившая любовь","18398":"Давайте танцевать","18399":"Кабульский экспресс"}