{"62610":"Поющее звенящее деревце","62611":"Поющие в терновнике. Часть 1 /По одноименному роману Коллин МакКалоу/","62612":"Поющие в терновнике. Часть 1 /По одноименному роману Коллин МакКалоу/","62613":"Поющие в терновнике. Часть 2 /По одноименному роману Коллин МакКалоу/","62614":"Поющие в терновнике. Часть 2 /По одноименному роману Коллин МакКалоу/","62615":"Поющие в терновнике. Часть 3 /По одноименному роману Коллин МакКалоу/","62616":"Поющие в терновнике. Часть 3 /По одноименному роману Коллин МакКалоу/","62617":"Поющие в терновнике. Часть 4 /По одноименному роману Коллин МакКалоу/","62618":"Поющие в терновнике. Часть 4 /По одноименному роману Коллин МакКалоу/","62619":"Поющие в терновнике:Пропавшие годы /По роману Коллин МакКаллоу/"}